.cvsignore
README
ez_setup.py
setup.cfg
setup.py
lib/dboptions.py
lib/docsql.py
lib/docsql.egg-info/PKG-INFO
lib/docsql.egg-info/SOURCES.txt
lib/docsql.egg-info/dependency_links.txt
lib/docsql.egg-info/requires.txt
lib/docsql.egg-info/top_level.txt
lib/docsql.egg-info/zip-safe