Metadata-Version: 1.0
Name: docsql
Version: 0.1.0a1
Summary: Easy access to Python DB API databases
Home-page: http://noble.gs.washington.edu/~mmh1/software/docsql/
Author: Michael Hoffman
Author-email: hoffman+docsql@ebi.ac.uk
License: GNU GPLv2
Download-URL: http://noble.gs.washington.edu/~mmh1/software/docsql/docsql-0.1.0a1.tar.gz
Platform: UNKNOWN
Classifier: License :: OSI Approved :: GNU General Public License (GPL)
Classifier: Natural Language :: English
Classifier: Programming Language :: Python
